wagtailcolumnblocks/__init__.py
wagtailcolumnblocks/blocks.py
wagtailcolumnblocks/static/wagtailcolumnblocks/columns.css
wagtailcolumnblocks/templates/block_forms/columnsblock.html
wagtailcolumnblocks/templates/blocks/columnsblock.html
wagtailcolumnblocks-2.3.1.dist-info/METADATA
wagtailcolumnblocks-2.3.1.dist-info/WHEEL
wagtailcolumnblocks-2.3.1.dist-info/top_level.txt
wagtailcolumnblocks-2.3.1.dist-info/RECORD
