Metadata-Version: 2.1
Name: wagtailcolumnblocks
Version: 2.3.1
Summary: Wagtail Column Blocks
Home-page: https://github.com/squareweave/wagtailcolumnblocks
Author: Squareweave
Author-email: hosting+pypi@squareweave.com.au
License: BSD
Platform: UNKNOWN
Classifier: Environment :: Web Environment
Classifier: License :: OSI Approved :: BSD License
Classifier: Programming Language :: Python
Classifier: Programming Language :: Python :: 3
Classifier: Programming Language :: Python :: 3.6
Classifier: Programming Language :: Python :: 3.7
Classifier: Programming Language :: Python :: 3.8
Classifier: Programming Language :: Python :: 3.9
Classifier: Framework :: Django :: 2.0
Classifier: Topic :: Internet :: WWW/HTTP :: Site Management
Requires-Dist: wagtail (>=2.10)
